alchemyjsonschema/__init__.py
alchemyjsonschema/debug.py
alchemyjsonschema/dictify.py
alchemyjsonschema/mapping.py
alchemyjsonschema/parser.py
alchemyjsonschema/command/__init__.py
alchemyjsonschema/command/_transformer.py
alchemyjsonschema/command/driver.py
alchemyjsonschema/command/main.py
alchemyjsonschema/custom/__init__.py
alchemyjsonschema/custom/format.py
alchemyjsonschema/custom/validator.py
mstax_alchemyjsonschema-1.0.0.dist-info/LICENSE
mstax_alchemyjsonschema-1.0.0.dist-info/METADATA
mstax_alchemyjsonschema-1.0.0.dist-info/WHEEL
mstax_alchemyjsonschema-1.0.0.dist-info/entry_points.txt
mstax_alchemyjsonschema-1.0.0.dist-info/top_level.txt
mstax_alchemyjsonschema-1.0.0.dist-info/RECORD
