Metadata-Version: 2.1
Name: mstax-alchemyjsonschema
Version: 1.0.0
Summary: A package for generating json-schema models from sqlalchemy models.
Home-page: https://github.com/splautz/alchemyjsonschema.git
Author: splautz
Author-email: 
License: mit
Keywords: alchemyjsonschema sqlalchemy jsonschema schema-generation
Classifier: Programming Language :: Python
Classifier: Programming Language :: Python :: Implementation :: CPython
License-File: LICENSE
Requires-Dist: sqlalchemy
Requires-Dist: jsonschema
Requires-Dist: strict-rfc3339
Requires-Dist: isodate
Requires-Dist: pytz
Requires-Dist: magicalimport
Requires-Dist: dictknife (>=0.7.2)
Provides-Extra: docs
Provides-Extra: testing
Requires-Dist: pytest ; extra == 'testing'
Requires-Dist: webob ; extra == 'testing'
